ztfy.sendit-0.1.20-py2.7-nspkg.pth
ztfy/sendit/__init__.py
ztfy/sendit/configure.zcml
ztfy/sendit/database.py
ztfy/sendit/security.zcml
ztfy/sendit/app/__init__.py
ztfy/sendit/app/configure.zcml
ztfy/sendit/app/filter.py
ztfy/sendit/app/browser/__init__.py
ztfy/sendit/app/browser/configure.zcml
ztfy/sendit/app/browser/json/__init__.py
ztfy/sendit/app/browser/json/configure.zcml
ztfy/sendit/app/browser/json/search.py
ztfy/sendit/app/interfaces/__init__.py
ztfy/sendit/app/interfaces/filter.py
ztfy/sendit/client/__init__.py
ztfy/sendit/client/configure.zcml
ztfy/sendit/client/browser/__init__.py
ztfy/sendit/client/browser/configure.zcml
ztfy/sendit/client/browser/json.py
ztfy/sendit/client/browser/widget.py
ztfy/sendit/client/interfaces/__init__.py
ztfy/sendit/doctests/README.txt
ztfy/sendit/generations/__init__.py
ztfy/sendit/generations/configure.zcml
ztfy/sendit/generations/evolve2.py
ztfy/sendit/generations/install.py
ztfy/sendit/locales/ztfy.sendit.pot
ztfy/sendit/locales/fr/LC_MESSAGES/ztfy.sendit.mo
ztfy/sendit/locales/fr/LC_MESSAGES/ztfy.sendit.po
ztfy/sendit/locales/fr/LC_MESSAGES/ztfy.sendit.po~
ztfy/sendit/packet/__init__.py
ztfy/sendit/packet/configure.zcml
ztfy/sendit/packet/events.py
ztfy/sendit/packet/filter.py
ztfy/sendit/packet/schema.py
ztfy/sendit/packet/task.py
ztfy/sendit/packet/browser/__init__.py
ztfy/sendit/packet/browser/configure.zcml
ztfy/sendit/packet/browser/filter.py
ztfy/sendit/packet/browser/task.py
ztfy/sendit/packet/browser/widget/__init__.py
ztfy/sendit/packet/browser/widget/configure.zcml
ztfy/sendit/packet/browser/widget/document.py
ztfy/sendit/packet/browser/widget/templates/document_display.pt
ztfy/sendit/packet/browser/widget/templates/document_input.pt
ztfy/sendit/packet/browser/widget/templates/documents_display.pt
ztfy/sendit/packet/browser/widget/templates/documents_input.pt
ztfy/sendit/packet/interfaces/__init__.py
ztfy/sendit/packet/interfaces/filter.py
ztfy.sendit-0.1.20.dist-info/DESCRIPTION.rst
ztfy.sendit-0.1.20.dist-info/METADATA
ztfy.sendit-0.1.20.dist-info/RECORD
ztfy.sendit-0.1.20.dist-info/WHEEL
ztfy.sendit-0.1.20.dist-info/entry_points.txt
ztfy.sendit-0.1.20.dist-info/metadata.json
ztfy.sendit-0.1.20.dist-info/namespace_packages.txt
ztfy.sendit-0.1.20.dist-info/top_level.txt
