Metadata-Version: 2.0
Name: ztfy.sendit
Version: 0.1.20
Summary: ZTFY application used to share files
Home-page: http://hg.ztfy.org/ztfy.sendit
Author: Thierry Florac
Author-email: tflorac@ulthar.net
License: zpl
Keywords: ZTFY sendit application
Platform: UNKNOWN
Classifier: Development Status :: 4 - Beta
Classifier: Framework :: ZODB
Classifier: Framework :: Zope3
Classifier: License :: OSI Approved :: Zope Public License
Classifier: Programming Language :: Python
Classifier: Topic :: Communications :: File Sharing
Classifier: Topic :: Internet :: WWW/HTTP :: WSGI
Requires-Dist: fanstatic
Requires-Dist: hurry.query
Requires-Dist: setuptools
Requires-Dist: uuid
Requires-Dist: z3c.form
Requires-Dist: z3c.formjs
Requires-Dist: z3c.jsonrpc
Requires-Dist: z3c.language.negotiator
Requires-Dist: z3c.language.switch
Requires-Dist: z3c.table
Requires-Dist: zc.catalog
Requires-Dist: zope.annotation
Requires-Dist: zope.app.content
Requires-Dist: zope.app.file
Requires-Dist: zope.app.publication
Requires-Dist: zope.authentication
Requires-Dist: zope.browserpage
Requires-Dist: zope.catalog
Requires-Dist: zope.component
Requires-Dist: zope.componentvocabulary
Requires-Dist: zope.container
Requires-Dist: zope.dublincore
Requires-Dist: zope.event
Requires-Dist: zope.i18n
Requires-Dist: zope.i18nmessageid
Requires-Dist: zope.interface
Requires-Dist: zope.intid
Requires-Dist: zope.lifecycleevent
Requires-Dist: zope.location
Requires-Dist: zope.pluggableauth
Requires-Dist: zope.principalannotation
Requires-Dist: zope.processlifetime
Requires-Dist: zope.publisher
Requires-Dist: zope.schema
Requires-Dist: zope.security
Requires-Dist: zope.sendmail
Requires-Dist: zope.site
Requires-Dist: zope.tales
Requires-Dist: zope.traversing
Requires-Dist: ztfy.appskin (>=0.2.0)
Requires-Dist: ztfy.captcha
Requires-Dist: ztfy.extfile (>=0.2.13)
Requires-Dist: ztfy.file
Requires-Dist: ztfy.i18n
Requires-Dist: ztfy.jqueryui
Requires-Dist: ztfy.mail
Requires-Dist: ztfy.scheduler
Requires-Dist: ztfy.security
Requires-Dist: ztfy.skin (>=0.6.0)
Requires-Dist: ztfy.utils (>=0.4.4)
Provides-Extra: test
Requires-Dist: zope.testing; extra == 'test'
